caipyrinha.py
ez_setup.py
setup.py
caipyrinha.egg-info/PKG-INFO
caipyrinha.egg-info/SOURCES.txt
caipyrinha.egg-info/dependency_links.txt
caipyrinha.egg-info/top_level.txt