Metadata-Version: 1.1
Name: caipyrinha
Version: 0.2.2
Summary: Abstraction layer over argparse.
Home-page: https://bitbucket.org/leliel12/caipyrinha
Author: JBC
Author-email: jbc dot develop at gmail dot com
License: WISKEY License
Download-URL: https://bitbucket.org/leliel12/caipyrinha/downloads/0.2.2-caipyrinha.tar.gz
Keywords: cli argparse argument parser optparse getopt
Platform: UNKNOWN
Classifier: Development Status :: 5 - Production/Stable
Classifier: Topic :: Utilities
Classifier: Operating System :: OS Independent
Classifier: Programming Language :: Python :: 2
